easy_cli/__init__.py
easy_cli/resources/__init__.py
easy_cli/resources/model.py
easy_cli/resources/repository.py
easy_cli/resources/utils.py
easy_cli/resources/views.py
easy_cli/scripts/__init__.py
easy_cli/scripts/easy_scripts.py
Flask_Easy_Cli-0.0.2.dist-info/METADATA
Flask_Easy_Cli-0.0.2.dist-info/WHEEL
Flask_Easy_Cli-0.0.2.dist-info/entry_points.txt
Flask_Easy_Cli-0.0.2.dist-info/top_level.txt
Flask_Easy_Cli-0.0.2.dist-info/RECORD
