Metadata-Version: 2.1
Name: Flask-Easy-Cli
Version: 0.0.2
Summary: UNKNOWN
Home-page: UNKNOWN
Author: Joseph Maclean Arhin
Author-email: me@josephmaclean.dev
License: BSD
Platform: UNKNOWN
Classifier: Environment :: Web Environment
Classifier: Intended Audience :: Developers
Classifier: License :: OSI Approved :: MIT License
Classifier: Operating System :: OS Independent
Classifier: Programming Language :: Python
Classifier: Topic :: Internet :: WWW/HTTP :: Dynamic Content
Classifier: Topic :: Software Development :: Libraries :: Python Modules
Requires-Python: >=3.8
Requires-Dist: Flask-Easy (>=0.0.1)
Requires-Dist: cookiecutter (>=1.7.3)
Requires-Dist: click (>=7.1.2)
Requires-Dist: jinja2 (>=3.0.3)
